chatterbox/.models.json
chatterbox/__init__.py
chatterbox/__main__.py
uq_chatterbox-0.1.1.dist-info/entry_points.txt
uq_chatterbox-0.1.1.dist-info/WHEEL
uq_chatterbox-0.1.1.dist-info/METADATA
uq_chatterbox-0.1.1.dist-info/RECORD
